{
    "apiVersion": 2,
    "name": "circus/contact-block",
    "title": "Contact Block",
    "category": "formatting",
    "icon": "phone",
    "description": "Contact information block with delivery, address, and catering details.",
    "keywords": [
        "contact",
        "phone",
        "address",
        "kontakt",
        "telefon"
    ],
    "acf": {
        "mode": "edit",
        "renderTemplate": "contact-block.php"
    },
    "supports": {
        "mode": true,
        "anchor": true,
        "jsx": true
    },
    "example": {
        "attributes": {
            "mode": "preview",
            "data": {
                "is_example": true
            }
        }
    }
}